burpa/__init__.py
burpa/__main__.py
burpa/__version__.py
burpa/_api_base.py
burpa/_burp_commander.py
burpa/_burp_rest_api_client.py
burpa/_burpa.py
burpa/_error.py
burpa/_utils.py
burpa/issue_defs.json
burpa-0.3.12.dist-info/licenses/LICENSE
burpa-0.3.12.dist-info/METADATA
burpa-0.3.12.dist-info/WHEEL
burpa-0.3.12.dist-info/entry_points.txt
burpa-0.3.12.dist-info/top_level.txt
burpa-0.3.12.dist-info/RECORD
