Metadata-Version: 2.4
Name: burpa
Version: 0.3.12
Author: Adel "0x4d31" Karimi, and other contributors
Requires-Python: >=3.6
License-File: LICENSE
Requires-Dist: requests>=2.4.2
Requires-Dist: attrs
Requires-Dist: fire
Requires-Dist: python-dotenv
Requires-Dist: filelock
Requires-Dist: python-dateutil
Requires-Dist: importlib_resources
Dynamic: author
Dynamic: description
Dynamic: description-content-type
Dynamic: license-file
Dynamic: requires-dist
Dynamic: requires-python
